{
  "output_location": "buddingcrystals:block/large_bud/nether_quartz",
  "input": {
    "source_type": "dynamic_asset_generator:combined_paletted_image",
    "overlay": {
      "source_type": "dynamic_asset_generator:color",
      "color": []
    },
    "background": {
      "source_type": "dynamic_asset_generator:texture",
      "path": "minecraft:item/quartz"
    },
    "paletted": {
      "source_type": "dynamic_asset_generator:texture",
      "path": "minecraft:block/large_amethyst_bud"
    },
    "include_background": false,
    "stretch_paletted": true,
    "extend_palette_size": 0
  }
}